reasoning_workbench/__init__.py
reasoning_workbench/main.py
reasoning_workbench-0.1.0.dist-info/METADATA
reasoning_workbench-0.1.0.dist-info/WHEEL
reasoning_workbench-0.1.0.dist-info/entry_points.txt
reasoning_workbench-0.1.0.dist-info/top_level.txt
reasoning_workbench-0.1.0.dist-info/RECORD
